[{"features": ["district", "floor_area_sqft", "has_view", "has_fireplace"], "n_features": 4, "model": "Random Forest", "r2": 78.5, "mae": 305724.0}, {"features": ["district", "floor_area_sqft", "has_view", "has_appliances"], "n_features": 4, "model": "Random Forest", "r2": 78.6, "mae": 305926.0}, {"features": ["district", "floor_area_sqft", "has_view", "style"], "n_features": 4, "model": "Random Forest", "r2": 78.7, "mae": 303802.0}, {"features": ["district", "floor_area_sqft", "has_view", "cooling_features"], "n_features": 4, "model": "Random Forest", "r2": 78.6, "mae": 303723.0}, {"features": ["district", "floor_area_sqft", "has_view", "appliances"], "n_features": 4, "model": "Random Forest", "r2": 78.3, "mae": 309950.0}, {"features": ["district", "floor_area_sqft", "has_fireplace", "has_parking_feat"], "n_features": 4, "model": "Random Forest", "r2": 78.5, "mae": 304870.0}, {"features": ["district", "floor_area_sqft", "has_fireplace", "property_type"], "n_features": 4, "model": "Random Forest", "r2": 78.5, "mae": 306291.0}, {"features": ["district", "floor_area_sqft", "has_fireplace", "parking_features"], "n_features": 4, "model": "Random Forest", "r2": 79.4, "mae": 292626.0}, {"features": ["district", "floor_area_sqft", "has_fireplace", "interior_features"], "n_features": 4, "model": "Random Forest", "r2": 78.2, "mae": 307803.0}, {"features": ["district", "floor_area_sqft", "has_cooling", "has_parking_feat"], "n_features": 4, "model": "Random Forest", "r2": 78.6, "mae": 303877.0}, {"features": ["district", "floor_area_sqft", "has_cooling", "property_type"], "n_features": 4, "model": "Random Forest", "r2": 78.6, "mae": 305710.0}, {"features": ["district", "floor_area_sqft", "has_cooling", "parking_features"], "n_features": 4, "model": "Random Forest", "r2": 79.5, "mae": 291997.0}, {"features": ["district", "floor_area_sqft", "has_cooling", "interior_features"], "n_features": 4, "model": "Random Forest", "r2": 78.3, "mae": 306536.0}, {"features": ["district", "floor_area_sqft", "has_parking_feat", "has_appliances"], "n_features": 4, "model": "Random Forest", "r2": 78.5, "mae": 304929.0}, {"features": ["district", "floor_area_sqft", "has_parking_feat", "style"], "n_features": 4, "model": "Random Forest", "r2": 78.6, "mae": 302579.0}, {"features": ["district", "floor_area_sqft", "has_parking_feat", "cooling_features"], "n_features": 4, "model": "Random Forest", "r2": 78.7, "mae": 302393.0}]