[{"features": ["district", "rooms", "bathrooms", "interior_features"], "n_features": 4, "model": "Random Forest", "r2": 77.0, "mae": 315473.0}, {"features": ["district", "rooms", "parking_spaces", "age"], "n_features": 4, "model": "Random Forest", "r2": 76.4, "mae": 320270.0}, {"features": ["district", "rooms", "parking_spaces", "bath_ratio"], "n_features": 4, "model": "Random Forest", "r2": 76.3, "mae": 313790.0}, {"features": ["district", "rooms", "parking_spaces", "has_cooling"], "n_features": 4, "model": "Random Forest", "r2": 76.3, "mae": 316466.0}, {"features": ["district", "rooms", "parking_spaces", "has_interior"], "n_features": 4, "model": "Random Forest", "r2": 77.0, "mae": 314515.0}, {"features": ["district", "rooms", "parking_spaces", "city"], "n_features": 4, "model": "Random Forest", "r2": 76.1, "mae": 317368.0}, {"features": ["district", "rooms", "parking_spaces", "fireplace_features"], "n_features": 4, "model": "Random Forest", "r2": 76.3, "mae": 317980.0}, {"features": ["district", "rooms", "parking_spaces", "view"], "n_features": 4, "model": "Random Forest", "r2": 76.9, "mae": 312118.0}, {"features": ["district", "rooms", "age", "bath_ratio"], "n_features": 4, "model": "Random Forest", "r2": 76.6, "mae": 318531.0}, {"features": ["district", "rooms", "age", "has_cooling"], "n_features": 4, "model": "Random Forest", "r2": 76.1, "mae": 320155.0}, {"features": ["district", "rooms", "age", "has_interior"], "n_features": 4, "model": "Random Forest", "r2": 76.9, "mae": 318779.0}, {"features": ["district", "rooms", "age", "city"], "n_features": 4, "model": "Random Forest", "r2": 75.6, "mae": 322973.0}, {"features": ["district", "rooms", "age", "fireplace_features"], "n_features": 4, "model": "Random Forest", "r2": 76.0, "mae": 323859.0}, {"features": ["district", "rooms", "age", "view"], "n_features": 4, "model": "Random Forest", "r2": 76.1, "mae": 319892.0}, {"features": ["district", "rooms", "lot_ratio", "has_view"], "n_features": 4, "model": "Random Forest", "r2": 77.8, "mae": 312645.0}, {"features": ["district", "rooms", "lot_ratio", "has_parking_feat"], "n_features": 4, "model": "Random Forest", "r2": 77.7, "mae": 313557.0}]